formas_spacy_stanza-1.0.5.dist-info/licenses/LICENSE
spacy_stanza/__init__.py
spacy_stanza/about.py
spacy_stanza/tokenizer.py
formas_spacy_stanza-1.0.5.dist-info/METADATA
formas_spacy_stanza-1.0.5.dist-info/WHEEL
formas_spacy_stanza-1.0.5.dist-info/entry_points.txt
formas_spacy_stanza-1.0.5.dist-info/top_level.txt
formas_spacy_stanza-1.0.5.dist-info/RECORD
